[
  {
    "id": "a95200bc-2964-4afe-b00a-5d2a0a9778b3",
    "ts": 1756903906,
    "title": "LATTICE",
    "description": "d",
    "tags": []
  },
  {
    "id": "5857e40b-78cf-401d-afc7-857afe0456fd",
    "ts": 1756903918,
    "title": "LATTICE",
    "description": "d",
    "tags": []
  },
  {
    "id": "af23233c-6458-4665-a0a4-c210b7c752fe",
    "ts": 1756904037,
    "title": "LATTICE",
    "description": "d",
    "tags": []
  },
  {
    "id": "6ee2c9ec-91ed-4a39-86f2-26fa36a0af7d",
    "ts": 1756905045,
    "title": "LATTICE",
    "description": "d",
    "tags": []
  },
  {
    "id": "f7318e64-23fa-4092-8221-5e6e9632b850",
    "ts": 1756906967,
    "title": "LATTICE",
    "description": "d",
    "tags": []
  },
  {
    "id": "5416ef3d-5a67-4235-893d-946c7b85dd38",
    "ts": 1756907435,
    "title": "LATTICE",
    "description": "d",
    "tags": []
  },
  {
    "id": "eda84b6b-07c1-448a-8a97-34e3d962ee06",
    "ts": 1756907791,
    "title": "LATTICE",
    "description": "d",
    "tags": []
  },
  {
    "id": "7407f45a-e4f3-4afe-ab18-b069536f5440",
    "ts": 1756908393,
    "title": "LATTICE",
    "description": "d",
    "tags": []
  },
  {
    "id": "6d078511-be45-48ea-bfcd-c4071bf72b1b",
    "ts": 1756908947,
    "title": "LATTICE",
    "description": "d",
    "tags": []
  },
  {
    "id": "676da7d8-32ff-4510-a6b1-a8514b43f25c",
    "ts": 1756909532,
    "title": "LATTICE",
    "description": "d",
    "tags": []
  },
  {
    "id": "3cf44e3a-1c6c-4059-9506-e97345a884b8",
    "ts": 1756909882,
    "title": "LATTICE",
    "description": "d",
    "tags": []
  },
  {
    "id": "de32e347-77e5-4515-ac15-06dbfac2a8a5",
    "ts": 1756912563,
    "title": "LATTICE",
    "description": "d",
    "tags": []
  },
  {
    "id": "416e52cd-b95b-4ea8-8d30-949181962a28",
    "ts": 1756912965,
    "title": "LATTICE",
    "description": "d",
    "tags": []
  },
  {
    "id": "6356bf49-32ea-4408-9971-eaa964f5b1c6",
    "ts": 1756912990,
    "title": "LATTICE",
    "description": "d",
    "tags": []
  },
  {
    "id": "0d626a0a-f8ab-497f-926e-a18aa4b6dbfc",
    "ts": 1756913971,
    "title": "LATTICE",
    "description": "d",
    "tags": []
  },
  {
    "id": "8e7f6d61-dda0-49da-8508-1394ee599063",
    "ts": 1756915173,
    "title": "LATTICE",
    "description": "d",
    "tags": []
  },
  {
    "id": "275b6e7e-3ba7-4910-a80e-fbc77c79bf4a",
    "ts": 1756915494,
    "title": "LATTICE",
    "description": "d",
    "tags": []
  },
  {
    "id": "c5b390fc-3592-4800-a225-8bfc20f72eea",
    "ts": 1756916213,
    "title": "LATTICE",
    "description": "d",
    "tags": []
  },
  {
    "id": "f9c85952-fa52-4a8f-858c-a2b0cda8a5bc",
    "ts": 1757765996,
    "title": "LATTICE",
    "description": "d",
    "tags": []
  },
  {
    "id": "7bc574fa-0c3e-420d-8bb4-585d815cceae",
    "ts": 1757766001,
    "title": "LATTICE",
    "description": "d",
    "tags": []
  },
  {
    "id": "7e430761-7e65-4fd2-89c2-217d6f98a403",
    "ts": 1757767723,
    "title": "LATTICE",
    "description": "d",
    "tags": []
  },
  {
    "id": "939c6090-8895-43d0-aa4d-4d24315b4de1",
    "ts": 1757768773,
    "title": "LATTICE",
    "description": "d",
    "tags": []
  },
  {
    "id": "0494610f-bb07-4ec6-a590-9ace20ec74d1",
    "ts": 1757768784,
    "title": "LATTICE",
    "description": "d",
    "tags": []
  },
  {
    "id": "efd8b5a9-a0f8-49f3-9207-4c391ff48bfb",
    "ts": 1757769715,
    "title": "LATTICE",
    "description": "d",
    "tags": []
  },
  {
    "id": "0d807bc5-ecfb-4357-91ce-d58f9833f5be",
    "ts": 1757952734,
    "title": "LATTICE",
    "description": "d",
    "tags": []
  },
  {
    "id": "86734624-1203-44f7-b013-f482bb92fe98",
    "ts": 1757952740,
    "title": "LATTICE",
    "description": "d",
    "tags": []
  },
  {
    "id": "3e802f93-6fc1-45bb-a393-2209bacd667a",
    "ts": 1757952745,
    "title": "LATTICE",
    "description": "d",
    "tags": []
  },
  {
    "id": "8295f940-1532-4057-b047-819d548fb7d8",
    "ts": 1757953962,
    "title": "LATTICE",
    "description": "d",
    "tags": []
  },
  {
    "id": "ece43d38-19c9-4e99-872b-43fa9146638e",
    "ts": 1757953991,
    "title": "LATTICE",
    "description": "d",
    "tags": []
  },
  {
    "id": "4392d823-5f21-49f3-ad2a-21b71110af1c",
    "ts": 1757955534,
    "title": "LATTICE",
    "description": "d",
    "tags": []
  },
  {
    "id": "b673c8b3-6f01-4478-a8fd-6380142c3502",
    "ts": 1757956511,
    "title": "LATTICE",
    "description": "d",
    "tags": []
  },
  {
    "id": "67ce2de5-a3f8-4faa-952a-27e02ee37acf",
    "ts": 1757957509,
    "title": "LATTICE",
    "description": "d",
    "tags": []
  },
  {
    "id": "992432be-f6c1-46f0-ab76-b8d8ba44412b",
    "ts": 1757957549,
    "title": "LATTICE",
    "description": "d",
    "tags": []
  },
  {
    "id": "90b3ab10-c40d-4de1-a72d-5a0512bf730f",
    "ts": 1770418217,
    "title": "LATTICE",
    "description": "d",
    "tags": []
  },
  {
    "id": "e08dcad1-b39d-40f6-ab89-6be300c9e180",
    "ts": 1770562343,
    "title": "LATTICE",
    "description": "d",
    "tags": []
  }
]
