[
  {
    "id": "02b6e91a-5d00-4989-b8d7-cfd8ddd040e7",
    "ts": 1756903906,
    "change": "home page",
    "repo": "https://github.com/smarthaus/site",
    "pr": null,
    "author": null
  },
  {
    "id": "504bba0a-f31a-4141-84c7-f7e12aa8002a",
    "ts": 1756903918,
    "change": "home page",
    "repo": "https://github.com/smarthaus/site",
    "pr": null,
    "author": null
  },
  {
    "id": "8161e366-27d7-4b6a-bb7d-d66178b009aa",
    "ts": 1756904037,
    "change": "home page",
    "repo": "https://github.com/smarthaus/site",
    "pr": null,
    "author": null
  },
  {
    "id": "a2fb1002-060e-4ebe-84a5-f80f3216a52c",
    "ts": 1756905045,
    "change": "home page",
    "repo": "https://github.com/smarthaus/site",
    "pr": null,
    "author": null
  },
  {
    "id": "479f9ceb-170f-4866-88a1-799222476df3",
    "ts": 1756906967,
    "change": "home page",
    "repo": "https://github.com/smarthaus/site",
    "pr": null,
    "author": null
  },
  {
    "id": "923ca17c-4b81-46bc-9661-004032c39b82",
    "ts": 1756907435,
    "change": "home page",
    "repo": "https://github.com/smarthaus/site",
    "pr": null,
    "author": null
  },
  {
    "id": "f0128094-cde0-40a2-8bcf-32409f71199d",
    "ts": 1756907791,
    "change": "home page",
    "repo": "https://github.com/smarthaus/site",
    "pr": null,
    "author": null
  },
  {
    "id": "e76290fd-41a7-49d3-b266-3cd79100c364",
    "ts": 1756908393,
    "change": "home page",
    "repo": "https://github.com/smarthaus/site",
    "pr": null,
    "author": null
  },
  {
    "id": "bce464c3-1c90-4068-b970-026d0d4d7cdc",
    "ts": 1756908947,
    "change": "home page",
    "repo": "https://github.com/smarthaus/site",
    "pr": null,
    "author": null
  },
  {
    "id": "9620a9ed-591b-4bbe-b436-3fe603571ed5",
    "ts": 1756909532,
    "change": "home page",
    "repo": "https://github.com/smarthaus/site",
    "pr": null,
    "author": null
  },
  {
    "id": "812db871-2f19-43d8-8614-0aa9632e4f8f",
    "ts": 1756909882,
    "change": "home page",
    "repo": "https://github.com/smarthaus/site",
    "pr": null,
    "author": null
  },
  {
    "id": "36829564-8949-4668-9fb6-b1c0643e6317",
    "ts": 1756912563,
    "change": "home page",
    "repo": "https://github.com/smarthaus/site",
    "pr": null,
    "author": null
  },
  {
    "id": "e1a24767-7a9e-4a61-9ef0-749db2a47e5c",
    "ts": 1756912965,
    "change": "home page",
    "repo": "https://github.com/smarthaus/site",
    "pr": null,
    "author": null
  },
  {
    "id": "745b6e99-ca5f-4e4c-9efe-337d0ffa1372",
    "ts": 1756912990,
    "change": "home page",
    "repo": "https://github.com/smarthaus/site",
    "pr": null,
    "author": null
  },
  {
    "id": "48c7473f-f130-4ea1-bba8-559fcc7da969",
    "ts": 1756913971,
    "change": "home page",
    "repo": "https://github.com/smarthaus/site",
    "pr": null,
    "author": null
  },
  {
    "id": "9d0eccc0-7932-470d-a820-2497e83a8742",
    "ts": 1756915173,
    "change": "home page",
    "repo": "https://github.com/smarthaus/site",
    "pr": null,
    "author": null
  },
  {
    "id": "9f544301-14fa-4510-9a83-0e32635bfffe",
    "ts": 1756915494,
    "change": "home page",
    "repo": "https://github.com/smarthaus/site",
    "pr": null,
    "author": null
  },
  {
    "id": "e38774da-16ec-4161-aafd-2052920319e9",
    "ts": 1756916213,
    "change": "home page",
    "repo": "https://github.com/smarthaus/site",
    "pr": null,
    "author": null
  },
  {
    "id": "f2bfc4bc-85c7-475b-a183-4ebb9a6ec539",
    "ts": 1757765965,
    "change": "home page",
    "repo": "https://github.com/smarthaus/site",
    "pr": null,
    "author": null
  },
  {
    "id": "1d9609a4-4788-404d-a742-d1c28bccba67",
    "ts": 1757766001,
    "change": "home page",
    "repo": "https://github.com/smarthaus/site",
    "pr": null,
    "author": null
  },
  {
    "id": "0d9bcc57-2fc0-46d7-958d-64b1f6f7693f",
    "ts": 1757767723,
    "change": "home page",
    "repo": "https://github.com/smarthaus/site",
    "pr": null,
    "author": null
  },
  {
    "id": "8f7a168b-98ab-4489-83ef-6bf51df32a83",
    "ts": 1757768773,
    "change": "home page",
    "repo": "https://github.com/smarthaus/site",
    "pr": null,
    "author": null
  },
  {
    "id": "dfeca9bc-2f7e-4034-a102-54ae563e5626",
    "ts": 1757768784,
    "change": "home page",
    "repo": "https://github.com/smarthaus/site",
    "pr": null,
    "author": null
  },
  {
    "id": "57e19451-0d7f-4db5-83d5-28c94a96560e",
    "ts": 1757769715,
    "change": "home page",
    "repo": "https://github.com/smarthaus/site",
    "pr": null,
    "author": null
  },
  {
    "id": "8fe38091-d321-44f8-9291-0a9e5f0470ff",
    "ts": 1757952734,
    "change": "home page",
    "repo": "https://github.com/smarthaus/site",
    "pr": null,
    "author": null
  },
  {
    "id": "acfefb97-519f-4b96-874d-866843c85682",
    "ts": 1757952740,
    "change": "home page",
    "repo": "https://github.com/smarthaus/site",
    "pr": null,
    "author": null
  },
  {
    "id": "c2b1103a-6e60-4ef6-a390-b1a2f4e1a2dc",
    "ts": 1757952745,
    "change": "home page",
    "repo": "https://github.com/smarthaus/site",
    "pr": null,
    "author": null
  },
  {
    "id": "c0801f17-dc7b-4122-bc6e-e1d7269bcdf1",
    "ts": 1757953962,
    "change": "home page",
    "repo": "https://github.com/smarthaus/site",
    "pr": null,
    "author": null
  },
  {
    "id": "eec748a4-09a0-44dc-a659-51a562ab4ed6",
    "ts": 1757953991,
    "change": "home page",
    "repo": "https://github.com/smarthaus/site",
    "pr": null,
    "author": null
  },
  {
    "id": "40b1057f-bc0b-43ff-a4df-9f4001505d04",
    "ts": 1757955534,
    "change": "home page",
    "repo": "https://github.com/smarthaus/site",
    "pr": null,
    "author": null
  },
  {
    "id": "7fcada0f-762f-4256-b8ec-2a29991c186c",
    "ts": 1757956511,
    "change": "home page",
    "repo": "https://github.com/smarthaus/site",
    "pr": null,
    "author": null
  },
  {
    "id": "a57888a2-20bb-480b-a377-c931d05aea65",
    "ts": 1757957509,
    "change": "home page",
    "repo": "https://github.com/smarthaus/site",
    "pr": null,
    "author": null
  },
  {
    "id": "166120ca-2d8e-4d85-9afe-006bfeccb3bf",
    "ts": 1757957549,
    "change": "home page",
    "repo": "https://github.com/smarthaus/site",
    "pr": null,
    "author": null
  },
  {
    "id": "b7b34718-9eb2-4a91-80cc-fe5ec20d3fa1",
    "ts": 1770562343,
    "change": "home page",
    "repo": "https://github.com/smarthaus/site",
    "pr": null,
    "author": null
  },
  {
    "id": "7f1384ea-365d-4464-b0ff-923a9587e3c7",
    "ts": 1775684483,
    "change": "home page",
    "repo": "https://github.com/smarthaus/site",
    "pr": null,
    "author": null
  }
]
